[
  {
    "id": "ip11-64-a80",
    "title": "iPhone 11 64GB Usado A+",
    "description": "iPhone 11 64GB · Usado A+ · Batería ≥80%. Garantía QRTech.",
    "availability": "in stock",
    "condition": "used",
    "price": "260.00 USD",
    "color": "",
    "size": "64GB",
    "custom_label_0": "≥80%",
    "item_group_id": "ip11",
    "brand": "Apple",
    "link": "https://qrtech.com.ar/productos?sku=ip11",
    "image_link": "https://qrtech.com.ar/img/productos/11.png",
    "additional_image_link": "",
    "google_product_category": "Móviles y accesorios > Teléfonos móviles"
  },
  {
    "id": "ip11-64-a90",
    "title": "iPhone 11 64GB Usado A+",
    "description": "iPhone 11 64GB · Usado A+ · Batería ≥90%. Garantía QRTech.",
    "availability": "in stock",
    "condition": "used",
    "price": "270.00 USD",
    "color": "",
    "size": "64GB",
    "custom_label_0": "≥90%",
    "item_group_id": "ip11",
    "brand": "Apple",
    "link": "https://qrtech.com.ar/productos?sku=ip11",
    "image_link": "https://qrtech.com.ar/img/productos/11.png",
    "additional_image_link": "",
    "google_product_category": "Móviles y accesorios > Teléfonos móviles"
  },
  {
    "id": "ip11-64-a100",
    "title": "iPhone 11 64GB Usado A+",
    "description": "iPhone 11 64GB · Usado A+ · Batería 100%. Garantía QRTech.",
    "availability": "in stock",
    "condition": "used",
    "price": "280.00 USD",
    "color": "",
    "size": "64GB",
    "custom_label_0": "100%",
    "item_group_id": "ip11",
    "brand": "Apple",
    "link": "https://qrtech.com.ar/productos?sku=ip11",
    "image_link": "https://qrtech.com.ar/img/productos/11.png",
    "additional_image_link": "",
    "google_product_category": "Móviles y accesorios > Teléfonos móviles"
  },
  {
    "id": "ip11-128-a85",
    "title": "iPhone 11 128GB Usado A+",
    "description": "iPhone 11 128GB · Usado A+ · Batería ≥85%. Garantía QRTech.",
    "availability": "in stock",
    "condition": "used",
    "price": "280.00 USD",
    "color": "",
    "size": "128GB",
    "custom_label_0": "≥85%",
    "item_group_id": "ip11",
    "brand": "Apple",
    "link": "https://qrtech.com.ar/productos?sku=ip11",
    "image_link": "https://qrtech.com.ar/img/productos/11.png",
    "additional_image_link": "",
    "google_product_category": "Móviles y accesorios > Teléfonos móviles"
  },
  {
    "id": "ip11-128-a90",
    "title": "iPhone 11 128GB Usado A+",
    "description": "iPhone 11 128GB · Usado A+ · Batería ≥90%. Garantía QRTech.",
    "availability": "in stock",
    "condition": "used",
    "price": "290.00 USD",
    "color": "",
    "size": "128GB",
    "custom_label_0": "≥90%",
    "item_group_id": "ip11",
    "brand": "Apple",
    "link": "https://qrtech.com.ar/productos?sku=ip11",
    "image_link": "https://qrtech.com.ar/img/productos/11.png",
    "additional_image_link": "",
    "google_product_category": "Móviles y accesorios > Teléfonos móviles"
  },
  {
    "id": "ip11-128-a100",
    "title": "iPhone 11 128GB Usado A+",
    "description": "iPhone 11 128GB · Usado A+ · Batería 100%. Garantía QRTech.",
    "availability": "in stock",
    "condition": "used",
    "price": "300.00 USD",
    "color": "",
    "size": "128GB",
    "custom_label_0": "100%",
    "item_group_id": "ip11",
    "brand": "Apple",
    "link": "https://qrtech.com.ar/productos?sku=ip11",
    "image_link": "https://qrtech.com.ar/img/productos/11.png",
    "additional_image_link": "",
    "google_product_category": "Móviles y accesorios > Teléfonos móviles"
  },
  {
    "id": "ip11p-64-a80",
    "title": "iPhone 11 Pro 64GB Usado A+",
    "description": "iPhone 11 Pro 64GB · Usado A+ · Batería ≥80%. Garantía QRTech.",
    "availability": "in stock",
    "condition": "used",
    "price": "290.00 USD",
    "color": "",
    "size": "64GB",
    "custom_label_0": "≥80%",
    "item_group_id": "ip11p",
    "brand": "Apple",
    "link": "https://qrtech.com.ar/productos?sku=ip11p",
    "image_link": "https://qrtech.com.ar/img/productos/11p.png",
    "additional_image_link": "",
    "google_product_category": "Móviles y accesorios > Teléfonos móviles"
  },
  {
    "id": "ip11p-64-a90",
    "title": "iPhone 11 Pro 64GB Usado A+",
    "description": "iPhone 11 Pro 64GB · Usado A+ · Batería ≥90%. Garantía QRTech.",
    "availability": "in stock",
    "condition": "used",
    "price": "300.00 USD",
    "color": "",
    "size": "64GB",
    "custom_label_0": "≥90%",
    "item_group_id": "ip11p",
    "brand": "Apple",
    "link": "https://qrtech.com.ar/productos?sku=ip11p",
    "image_link": "https://qrtech.com.ar/img/productos/11p.png",
    "additional_image_link": "",
    "google_product_category": "Móviles y accesorios > Teléfonos móviles"
  },
  {
    "id": "ip11p-64-a100",
    "title": "iPhone 11 Pro 64GB Usado A+",
    "description": "iPhone 11 Pro 64GB · Usado A+ · Batería 100%. Garantía QRTech.",
    "availability": "in stock",
    "condition": "used",
    "price": "310.00 USD",
    "color": "",
    "size": "64GB",
    "custom_label_0": "100%",
    "item_group_id": "ip11p",
    "brand": "Apple",
    "link": "https://qrtech.com.ar/productos?sku=ip11p",
    "image_link": "https://qrtech.com.ar/img/productos/11p.png",
    "additional_image_link": "",
    "google_product_category": "Móviles y accesorios > Teléfonos móviles"
  },
  {
    "id": "ip11p-128-a80",
    "title": "iPhone 11 Pro 128GB Usado A+",
    "description": "iPhone 11 Pro 128GB · Usado A+ · Batería ≥85%. Garantía QRTech.",
    "availability": "in stock",
    "condition": "used",
    "price": "300.00 USD",
    "color": "",
    "size": "128GB",
    "custom_label_0": "≥85%",
    "item_group_id": "ip11p",
    "brand": "Apple",
    "link": "https://qrtech.com.ar/productos?sku=ip11p",
    "image_link": "https://qrtech.com.ar/img/productos/11p.png",
    "additional_image_link": "",
    "google_product_category": "Móviles y accesorios > Teléfonos móviles"
  },
  {
    "id": "ip11p-128-a90",
    "title": "iPhone 11 Pro 128GB Usado A+",
    "description": "iPhone 11 Pro 128GB · Usado A+ · Batería ≥90%. Garantía QRTech.",
    "availability": "in stock",
    "condition": "used",
    "price": "310.00 USD",
    "color": "",
    "size": "128GB",
    "custom_label_0": "≥90%",
    "item_group_id": "ip11p",
    "brand": "Apple",
    "link": "https://qrtech.com.ar/productos?sku=ip11p",
    "image_link": "https://qrtech.com.ar/img/productos/11p.png",
    "additional_image_link": "",
    "google_product_category": "Móviles y accesorios > Teléfonos móviles"
  },
  {
    "id": "ip11p-128-a100",
    "title": "iPhone 11 Pro 128GB Usado A+",
    "description": "iPhone 11 Pro 128GB · Usado A+ · Batería 100%. Garantía QRTech.",
    "availability": "in stock",
    "condition": "used",
    "price": "320.00 USD",
    "color": "",
    "size": "128GB",
    "custom_label_0": "100%",
    "item_group_id": "ip11p",
    "brand": "Apple",
    "link": "https://qrtech.com.ar/productos?sku=ip11p",
    "image_link": "https://qrtech.com.ar/img/productos/11p.png",
    "additional_image_link": "",
    "google_product_category": "Móviles y accesorios > Teléfonos móviles"
  },
  {
    "id": "ip11pm-64-a80",
    "title": "iPhone 11 Pro Max 64GB Usado A+",
    "description": "iPhone 11 Pro Max 64GB · Usado A+ · Batería ≥80%. Garantía QRTech.",
    "availability": "in stock",
    "condition": "used",
    "price": "300.00 USD",
    "color": "",
    "size": "64GB",
    "custom_label_0": "≥80%",
    "item_group_id": "ip11pm",
    "brand": "Apple",
    "link": "https://qrtech.com.ar/productos?sku=ip11pm",
    "image_link": "https://qrtech.com.ar/img/productos/11pm.png",
    "additional_image_link": "",
    "google_product_category": "Móviles y accesorios > Teléfonos móviles"
  },
  {
    "id": "ip11pm-64-a90",
    "title": "iPhone 11 Pro Max 64GB Usado A+",
    "description": "iPhone 11 Pro Max 64GB · Usado A+ · Batería ≥90%. Garantía QRTech.",
    "availability": "in stock",
    "condition": "used",
    "price": "310.00 USD",
    "color": "",
    "size": "64GB",
    "custom_label_0": "≥90%",
    "item_group_id": "ip11pm",
    "brand": "Apple",
    "link": "https://qrtech.com.ar/productos?sku=ip11pm",
    "image_link": "https://qrtech.com.ar/img/productos/11pm.png",
    "additional_image_link": "",
    "google_product_category": "Móviles y accesorios > Teléfonos móviles"
  },
  {
    "id": "ip11pm-64-a100",
    "title": "iPhone 11 Pro Max 64GB Usado A+",
    "description": "iPhone 11 Pro Max 64GB · Usado A+ · Batería 100%. Garantía QRTech.",
    "availability": "in stock",
    "condition": "used",
    "price": "320.00 USD",
    "color": "",
    "size": "64GB",
    "custom_label_0": "100%",
    "item_group_id": "ip11pm",
    "brand": "Apple",
    "link": "https://qrtech.com.ar/productos?sku=ip11pm",
    "image_link": "https://qrtech.com.ar/img/productos/11pm.png",
    "additional_image_link": "",
    "google_product_category": "Móviles y accesorios > Teléfonos móviles"
  },
  {
    "id": "ip11pm-128-a80",
    "title": "iPhone 11 Pro Max 128GB Usado A+",
    "description": "iPhone 11 Pro Max 128GB · Usado A+ · Batería ≥85%. Garantía QRTech.",
    "availability": "in stock",
    "condition": "used",
    "price": "310.00 USD",
    "color": "",
    "size": "128GB",
    "custom_label_0": "≥85%",
    "item_group_id": "ip11pm",
    "brand": "Apple",
    "link": "https://qrtech.com.ar/productos?sku=ip11pm",
    "image_link": "https://qrtech.com.ar/img/productos/11pm.png",
    "additional_image_link": "",
    "google_product_category": "Móviles y accesorios > Teléfonos móviles"
  },
  {
    "id": "ip11pm-128-a90",
    "title": "iPhone 11 Pro Max 128GB Usado A+",
    "description": "iPhone 11 Pro Max 128GB · Usado A+ · Batería ≥90%. Garantía QRTech.",
    "availability": "in stock",
    "condition": "used",
    "price": "320.00 USD",
    "color": "",
    "size": "128GB",
    "custom_label_0": "≥90%",
    "item_group_id": "ip11pm",
    "brand": "Apple",
    "link": "https://qrtech.com.ar/productos?sku=ip11pm",
    "image_link": "https://qrtech.com.ar/img/productos/11pm.png",
    "additional_image_link": "",
    "google_product_category": "Móviles y accesorios > Teléfonos móviles"
  },
  {
    "id": "ip11pm-128-a100",
    "title": "iPhone 11 Pro Max 128GB Usado A+",
    "description": "iPhone 11 Pro Max 128GB · Usado A+ · Batería 100%. Garantía QRTech.",
    "availability": "in stock",
    "condition": "used",
    "price": "330.00 USD",
    "color": "",
    "size": "128GB",
    "custom_label_0": "100%",
    "item_group_id": "ip11pm",
    "brand": "Apple",
    "link": "https://qrtech.com.ar/productos?sku=ip11pm",
    "image_link": "https://qrtech.com.ar/img/productos/11pm.png",
    "additional_image_link": "",
    "google_product_category": "Móviles y accesorios > Teléfonos móviles"
  },
  {
    "id": "ip12-64-a80",
    "title": "iPhone 12 64GB Usado A+",
    "description": "iPhone 12 64GB · Usado A+ · Batería ≥80%. Garantía QRTech.",
    "availability": "in stock",
    "condition": "used",
    "price": "300.00 USD",
    "color": "",
    "size": "64GB",
    "custom_label_0": "≥80%",
    "item_group_id": "ip12",
    "brand": "Apple",
    "link": "https://qrtech.com.ar/productos?sku=ip12",
    "image_link": "https://qrtech.com.ar/img/productos/12.png",
    "additional_image_link": "",
    "google_product_category": "Móviles y accesorios > Teléfonos móviles"
  },
  {
    "id": "ip12-64-a90",
    "title": "iPhone 12 64GB Usado A+",
    "description": "iPhone 12 64GB · Usado A+ · Batería ≥90%. Garantía QRTech.",
    "availability": "in stock",
    "condition": "used",
    "price": "310.00 USD",
    "color": "",
    "size": "64GB",
    "custom_label_0": "≥90%",
    "item_group_id": "ip12",
    "brand": "Apple",
    "link": "https://qrtech.com.ar/productos?sku=ip12",
    "image_link": "https://qrtech.com.ar/img/productos/12.png",
    "additional_image_link": "",
    "google_product_category": "Móviles y accesorios > Teléfonos móviles"
  },
  {
    "id": "ip12-64-a100",
    "title": "iPhone 12 64GB Usado A+",
    "description": "iPhone 12 64GB · Usado A+ · Batería 100%. Garantía QRTech.",
    "availability": "in stock",
    "condition": "used",
    "price": "320.00 USD",
    "color": "",
    "size": "64GB",
    "custom_label_0": "100%",
    "item_group_id": "ip12",
    "brand": "Apple",
    "link": "https://qrtech.com.ar/productos?sku=ip12",
    "image_link": "https://qrtech.com.ar/img/productos/12.png",
    "additional_image_link": "",
    "google_product_category": "Móviles y accesorios > Teléfonos móviles"
  },
  {
    "id": "ip12-128-a80",
    "title": "iPhone 12 128GB Usado A+",
    "description": "iPhone 12 128GB · Usado A+ · Batería ≥85%. Garantía QRTech.",
    "availability": "in stock",
    "condition": "used",
    "price": "310.00 USD",
    "color": "",
    "size": "128GB",
    "custom_label_0": "≥85%",
    "item_group_id": "ip12",
    "brand": "Apple",
    "link": "https://qrtech.com.ar/productos?sku=ip12",
    "image_link": "https://qrtech.com.ar/img/productos/12.png",
    "additional_image_link": "",
    "google_product_category": "Móviles y accesorios > Teléfonos móviles"
  },
  {
    "id": "ip12-128-a90",
    "title": "iPhone 12 128GB Usado A+",
    "description": "iPhone 12 128GB · Usado A+ · Batería ≥90%. Garantía QRTech.",
    "availability": "in stock",
    "condition": "used",
    "price": "320.00 USD",
    "color": "",
    "size": "128GB",
    "custom_label_0": "≥90%",
    "item_group_id": "ip12",
    "brand": "Apple",
    "link": "https://qrtech.com.ar/productos?sku=ip12",
    "image_link": "https://qrtech.com.ar/img/productos/12.png",
    "additional_image_link": "",
    "google_product_category": "Móviles y accesorios > Teléfonos móviles"
  },
  {
    "id": "ip12-128-a100",
    "title": "iPhone 12 128GB Usado A+",
    "description": "iPhone 12 128GB · Usado A+ · Batería 100%. Garantía QRTech.",
    "availability": "in stock",
    "condition": "used",
    "price": "330.00 USD",
    "color": "",
    "size": "128GB",
    "custom_label_0": "100%",
    "item_group_id": "ip12",
    "brand": "Apple",
    "link": "https://qrtech.com.ar/productos?sku=ip12",
    "image_link": "https://qrtech.com.ar/img/productos/12.png",
    "additional_image_link": "",
    "google_product_category": "Móviles y accesorios > Teléfonos móviles"
  },
  {
    "id": "ip12p-128-a80",
    "title": "iPhone 12 Pro 128GB Usado A+",
    "description": "iPhone 12 Pro 128GB · Usado A+ · Batería ≥85%. Garantía QRTech.",
    "availability": "in stock",
    "condition": "used",
    "price": "370.00 USD",
    "color": "",
    "size": "128GB",
    "custom_label_0": "≥85%",
    "item_group_id": "ip12p",
    "brand": "Apple",
    "link": "https://qrtech.com.ar/productos?sku=ip12p",
    "image_link": "https://qrtech.com.ar/img/productos/12p.png",
    "additional_image_link": "",
    "google_product_category": "Móviles y accesorios > Teléfonos móviles"
  },
  {
    "id": "ip12p-128-a90",
    "title": "iPhone 12 Pro 128GB Usado A+",
    "description": "iPhone 12 Pro 128GB · Usado A+ · Batería ≥90%. Garantía QRTech.",
    "availability": "in stock",
    "condition": "used",
    "price": "380.00 USD",
    "color": "",
    "size": "128GB",
    "custom_label_0": "≥90%",
    "item_group_id": "ip12p",
    "brand": "Apple",
    "link": "https://qrtech.com.ar/productos?sku=ip12p",
    "image_link": "https://qrtech.com.ar/img/productos/12p.png",
    "additional_image_link": "",
    "google_product_category": "Móviles y accesorios > Teléfonos móviles"
  },
  {
    "id": "ip12p-128-a100",
    "title": "iPhone 12 Pro 128GB Usado A+",
    "description": "iPhone 12 Pro 128GB · Usado A+ · Batería 100%. Garantía QRTech.",
    "availability": "in stock",
    "condition": "used",
    "price": "400.00 USD",
    "color": "",
    "size": "128GB",
    "custom_label_0": "100%",
    "item_group_id": "ip12p",
    "brand": "Apple",
    "link": "https://qrtech.com.ar/productos?sku=ip12p",
    "image_link": "https://qrtech.com.ar/img/productos/12p.png",
    "additional_image_link": "",
    "google_product_category": "Móviles y accesorios > Teléfonos móviles"
  },
  {
    "id": "ip12pm-128-a80",
    "title": "iPhone 12 Pro Max 128GB Usado A+",
    "description": "iPhone 12 Pro Max 128GB · Usado A+ · Batería ≥85%. Garantía QRTech.",
    "availability": "in stock",
    "condition": "used",
    "price": "400.00 USD",
    "color": "",
    "size": "128GB",
    "custom_label_0": "≥85%",
    "item_group_id": "ip12pm",
    "brand": "Apple",
    "link": "https://qrtech.com.ar/productos?sku=ip12pm",
    "image_link": "https://qrtech.com.ar/img/productos/12pm.png",
    "additional_image_link": "",
    "google_product_category": "Móviles y accesorios > Teléfonos móviles"
  },
  {
    "id": "ip12pm-128-a90",
    "title": "iPhone 12 Pro Max 128GB Usado A+",
    "description": "iPhone 12 Pro Max 128GB · Usado A+ · Batería ≥90%. Garantía QRTech.",
    "availability": "in stock",
    "condition": "used",
    "price": "410.00 USD",
    "color": "",
    "size": "128GB",
    "custom_label_0": "≥90%",
    "item_group_id": "ip12pm",
    "brand": "Apple",
    "link": "https://qrtech.com.ar/productos?sku=ip12pm",
    "image_link": "https://qrtech.com.ar/img/productos/12pm.png",
    "additional_image_link": "",
    "google_product_category": "Móviles y accesorios > Teléfonos móviles"
  },
  {
    "id": "ip12pm-128-a100",
    "title": "iPhone 12 Pro Max 128GB Usado A+",
    "description": "iPhone 12 Pro Max 128GB · Usado A+ · Batería 100%. Garantía QRTech.",
    "availability": "in stock",
    "condition": "used",
    "price": "430.00 USD",
    "color": "",
    "size": "128GB",
    "custom_label_0": "100%",
    "item_group_id": "ip12pm",
    "brand": "Apple",
    "link": "https://qrtech.com.ar/productos?sku=ip12pm",
    "image_link": "https://qrtech.com.ar/img/productos/12pm.png",
    "additional_image_link": "",
    "google_product_category": "Móviles y accesorios > Teléfonos móviles"
  },
  {
    "id": "ip13-128-a80",
    "title": "iPhone 13 128GB Usado A+",
    "description": "iPhone 13 128GB · Usado A+ · Batería ≥85%. Garantía QRTech.",
    "availability": "in stock",
    "condition": "used",
    "price": "400.00 USD",
    "color": "",
    "size": "128GB",
    "custom_label_0": "≥85%",
    "item_group_id": "ip13",
    "brand": "Apple",
    "link": "https://qrtech.com.ar/productos?sku=ip13",
    "image_link": "https://qrtech.com.ar/img/productos/13.png",
    "additional_image_link": "",
    "google_product_category": "Móviles y accesorios > Teléfonos móviles"
  },
  {
    "id": "ip13-128-a90",
    "title": "iPhone 13 128GB Usado A+",
    "description": "iPhone 13 128GB · Usado A+ · Batería ≥90%. Garantía QRTech.",
    "availability": "in stock",
    "condition": "used",
    "price": "410.00 USD",
    "color": "",
    "size": "128GB",
    "custom_label_0": "≥90%",
    "item_group_id": "ip13",
    "brand": "Apple",
    "link": "https://qrtech.com.ar/productos?sku=ip13",
    "image_link": "https://qrtech.com.ar/img/productos/13.png",
    "additional_image_link": "",
    "google_product_category": "Móviles y accesorios > Teléfonos móviles"
  },
  {
    "id": "ip13-128-a100",
    "title": "iPhone 13 128GB Usado A+",
    "description": "iPhone 13 128GB · Usado A+ · Batería 100%. Garantía QRTech.",
    "availability": "in stock",
    "condition": "used",
    "price": "430.00 USD",
    "color": "",
    "size": "128GB",
    "custom_label_0": "100%",
    "item_group_id": "ip13",
    "brand": "Apple",
    "link": "https://qrtech.com.ar/productos?sku=ip13",
    "image_link": "https://qrtech.com.ar/img/productos/13.png",
    "additional_image_link": "",
    "google_product_category": "Móviles y accesorios > Teléfonos móviles"
  },
  {
    "id": "ip13-128-sellado",
    "title": "iPhone 13 128GB Sellado",
    "description": "iPhone 13 128GB · Sellado · Batería sellado. Garantía QRTech.",
    "availability": "in stock",
    "condition": "new",
    "price": "570.00 USD",
    "color": "",
    "size": "128GB",
    "custom_label_0": "sellado",
    "item_group_id": "ip13",
    "brand": "Apple",
    "link": "https://qrtech.com.ar/productos?sku=ip13",
    "image_link": "https://qrtech.com.ar/img/productos/13.png",
    "additional_image_link": "",
    "google_product_category": "Móviles y accesorios > Teléfonos móviles"
  },
  {
    "id": "ip13p-128-a80",
    "title": "iPhone 13 Pro 128GB Usado A+",
    "description": "iPhone 13 Pro 128GB · Usado A+ · Batería ≥85%. Garantía QRTech.",
    "availability": "in stock",
    "condition": "used",
    "price": "500.00 USD",
    "color": "",
    "size": "128GB",
    "custom_label_0": "≥85%",
    "item_group_id": "ip13p",
    "brand": "Apple",
    "link": "https://qrtech.com.ar/productos?sku=ip13p",
    "image_link": "https://qrtech.com.ar/img/productos/13p.png",
    "additional_image_link": "",
    "google_product_category": "Móviles y accesorios > Teléfonos móviles"
  },
  {
    "id": "ip13p-128-a90",
    "title": "iPhone 13 Pro 128GB Usado A+",
    "description": "iPhone 13 Pro 128GB · Usado A+ · Batería ≥90%. Garantía QRTech.",
    "availability": "in stock",
    "condition": "used",
    "price": "510.00 USD",
    "color": "",
    "size": "128GB",
    "custom_label_0": "≥90%",
    "item_group_id": "ip13p",
    "brand": "Apple",
    "link": "https://qrtech.com.ar/productos?sku=ip13p",
    "image_link": "https://qrtech.com.ar/img/productos/13p.png",
    "additional_image_link": "",
    "google_product_category": "Móviles y accesorios > Teléfonos móviles"
  },
  {
    "id": "ip13p-128-a100",
    "title": "iPhone 13 Pro 128GB Usado A+",
    "description": "iPhone 13 Pro 128GB · Usado A+ · Batería 100%. Garantía QRTech.",
    "availability": "in stock",
    "condition": "used",
    "price": "540.00 USD",
    "color": "",
    "size": "128GB",
    "custom_label_0": "100%",
    "item_group_id": "ip13p",
    "brand": "Apple",
    "link": "https://qrtech.com.ar/productos?sku=ip13p",
    "image_link": "https://qrtech.com.ar/img/productos/13p.png",
    "additional_image_link": "",
    "google_product_category": "Móviles y accesorios > Teléfonos móviles"
  },
  {
    "id": "ip13pm-128-a80",
    "title": "iPhone 13 Pro Max 128GB Usado A+",
    "description": "iPhone 13 Pro Max 128GB · Usado A+ · Batería ≥85%. Garantía QRTech.",
    "availability": "in stock",
    "condition": "used",
    "price": "560.00 USD",
    "color": "",
    "size": "128GB",
    "custom_label_0": "≥85%",
    "item_group_id": "ip13pm",
    "brand": "Apple",
    "link": "https://qrtech.com.ar/productos?sku=ip13pm",
    "image_link": "https://qrtech.com.ar/img/productos/13pm.png",
    "additional_image_link": "",
    "google_product_category": "Móviles y accesorios > Teléfonos móviles"
  },
  {
    "id": "ip13pm-128-a90",
    "title": "iPhone 13 Pro Max 128GB Usado A+",
    "description": "iPhone 13 Pro Max 128GB · Usado A+ · Batería ≥90%. Garantía QRTech.",
    "availability": "in stock",
    "condition": "used",
    "price": "570.00 USD",
    "color": "",
    "size": "128GB",
    "custom_label_0": "≥90%",
    "item_group_id": "ip13pm",
    "brand": "Apple",
    "link": "https://qrtech.com.ar/productos?sku=ip13pm",
    "image_link": "https://qrtech.com.ar/img/productos/13pm.png",
    "additional_image_link": "",
    "google_product_category": "Móviles y accesorios > Teléfonos móviles"
  },
  {
    "id": "ip13pm-128-a100",
    "title": "iPhone 13 Pro Max 128GB Usado A+",
    "description": "iPhone 13 Pro Max 128GB · Usado A+ · Batería 100%. Garantía QRTech.",
    "availability": "in stock",
    "condition": "used",
    "price": "590.00 USD",
    "color": "",
    "size": "128GB",
    "custom_label_0": "100%",
    "item_group_id": "ip13pm",
    "brand": "Apple",
    "link": "https://qrtech.com.ar/productos?sku=ip13pm",
    "image_link": "https://qrtech.com.ar/img/productos/13pm.png",
    "additional_image_link": "",
    "google_product_category": "Móviles y accesorios > Teléfonos móviles"
  },
  {
    "id": "ip14-128-a80",
    "title": "iPhone 14 128GB Usado A+",
    "description": "iPhone 14 128GB · Usado A+ · Batería ≥85%. Garantía QRTech.",
    "availability": "in stock",
    "condition": "used",
    "price": "460.00 USD",
    "color": "",
    "size": "128GB",
    "custom_label_0": "≥85%",
    "item_group_id": "ip14",
    "brand": "Apple",
    "link": "https://qrtech.com.ar/productos?sku=ip14",
    "image_link": "https://qrtech.com.ar/img/productos/14.png",
    "additional_image_link": "",
    "google_product_category": "Móviles y accesorios > Teléfonos móviles"
  },
  {
    "id": "ip14-128-a90",
    "title": "iPhone 14 128GB Usado A+",
    "description": "iPhone 14 128GB · Usado A+ · Batería ≥90%. Garantía QRTech.",
    "availability": "in stock",
    "condition": "used",
    "price": "470.00 USD",
    "color": "",
    "size": "128GB",
    "custom_label_0": "≥90%",
    "item_group_id": "ip14",
    "brand": "Apple",
    "link": "https://qrtech.com.ar/productos?sku=ip14",
    "image_link": "https://qrtech.com.ar/img/productos/14.png",
    "additional_image_link": "",
    "google_product_category": "Móviles y accesorios > Teléfonos móviles"
  },
  {
    "id": "ip14-128-a100",
    "title": "iPhone 14 128GB Usado A+",
    "description": "iPhone 14 128GB · Usado A+ · Batería 100%. Garantía QRTech.",
    "availability": "in stock",
    "condition": "used",
    "price": "490.00 USD",
    "color": "",
    "size": "128GB",
    "custom_label_0": "100%",
    "item_group_id": "ip14",
    "brand": "Apple",
    "link": "https://qrtech.com.ar/productos?sku=ip14",
    "image_link": "https://qrtech.com.ar/img/productos/14.png",
    "additional_image_link": "",
    "google_product_category": "Móviles y accesorios > Teléfonos móviles"
  },
  {
    "id": "ip14p-128-a80",
    "title": "iPhone 14 Pro 128GB Usado A+",
    "description": "iPhone 14 Pro 128GB · Usado A+ · Batería ≥85%. Garantía QRTech.",
    "availability": "in stock",
    "condition": "used",
    "price": "590.00 USD",
    "color": "",
    "size": "128GB",
    "custom_label_0": "≥85%",
    "item_group_id": "ip14p",
    "brand": "Apple",
    "link": "https://qrtech.com.ar/productos?sku=ip14p",
    "image_link": "https://qrtech.com.ar/img/productos/14p.png",
    "additional_image_link": "",
    "google_product_category": "Móviles y accesorios > Teléfonos móviles"
  },
  {
    "id": "ip14p-128-a90",
    "title": "iPhone 14 Pro 128GB Usado A+",
    "description": "iPhone 14 Pro 128GB · Usado A+ · Batería ≥90%. Garantía QRTech.",
    "availability": "in stock",
    "condition": "used",
    "price": "600.00 USD",
    "color": "",
    "size": "128GB",
    "custom_label_0": "≥90%",
    "item_group_id": "ip14p",
    "brand": "Apple",
    "link": "https://qrtech.com.ar/productos?sku=ip14p",
    "image_link": "https://qrtech.com.ar/img/productos/14p.png",
    "additional_image_link": "",
    "google_product_category": "Móviles y accesorios > Teléfonos móviles"
  },
  {
    "id": "ip14p-128-a100",
    "title": "iPhone 14 Pro 128GB Usado A+",
    "description": "iPhone 14 Pro 128GB · Usado A+ · Batería 100%. Garantía QRTech.",
    "availability": "in stock",
    "condition": "used",
    "price": "630.00 USD",
    "color": "",
    "size": "128GB",
    "custom_label_0": "100%",
    "item_group_id": "ip14p",
    "brand": "Apple",
    "link": "https://qrtech.com.ar/productos?sku=ip14p",
    "image_link": "https://qrtech.com.ar/img/productos/14p.png",
    "additional_image_link": "",
    "google_product_category": "Móviles y accesorios > Teléfonos móviles"
  },
  {
    "id": "ip14pm-128-a80",
    "title": "iPhone 14 Pro Max 128GB Usado A+",
    "description": "iPhone 14 Pro Max 128GB · Usado A+ · Batería ≥85%. Garantía QRTech.",
    "availability": "in stock",
    "condition": "used",
    "price": "670.00 USD",
    "color": "",
    "size": "128GB",
    "custom_label_0": "≥85%",
    "item_group_id": "ip14pm",
    "brand": "Apple",
    "link": "https://qrtech.com.ar/productos?sku=ip14pm",
    "image_link": "https://qrtech.com.ar/img/productos/14pm.png",
    "additional_image_link": "",
    "google_product_category": "Móviles y accesorios > Teléfonos móviles"
  },
  {
    "id": "ip14pm-128-a90",
    "title": "iPhone 14 Pro Max 128GB Usado A+",
    "description": "iPhone 14 Pro Max 128GB · Usado A+ · Batería ≥90%. Garantía QRTech.",
    "availability": "in stock",
    "condition": "used",
    "price": "680.00 USD",
    "color": "",
    "size": "128GB",
    "custom_label_0": "≥90%",
    "item_group_id": "ip14pm",
    "brand": "Apple",
    "link": "https://qrtech.com.ar/productos?sku=ip14pm",
    "image_link": "https://qrtech.com.ar/img/productos/14pm.png",
    "additional_image_link": "",
    "google_product_category": "Móviles y accesorios > Teléfonos móviles"
  },
  {
    "id": "ip14pm-128-a100",
    "title": "iPhone 14 Pro Max 128GB Usado A+",
    "description": "iPhone 14 Pro Max 128GB · Usado A+ · Batería 100%. Garantía QRTech.",
    "availability": "in stock",
    "condition": "used",
    "price": "700.00 USD",
    "color": "",
    "size": "128GB",
    "custom_label_0": "100%",
    "item_group_id": "ip14pm",
    "brand": "Apple",
    "link": "https://qrtech.com.ar/productos?sku=ip14pm",
    "image_link": "https://qrtech.com.ar/img/productos/14pm.png",
    "additional_image_link": "",
    "google_product_category": "Móviles y accesorios > Teléfonos móviles"
  },
  {
    "id": "ip15-128-a80",
    "title": "iPhone 15 128GB Usado A+",
    "description": "iPhone 15 128GB · Usado A+ · Batería ≥85%. Garantía QRTech.",
    "availability": "in stock",
    "condition": "used",
    "price": "590.00 USD",
    "color": "",
    "size": "128GB",
    "custom_label_0": "≥85%",
    "item_group_id": "ip15",
    "brand": "Apple",
    "link": "https://qrtech.com.ar/productos?sku=ip15",
    "image_link": "https://qrtech.com.ar/img/productos/15.png",
    "additional_image_link": "",
    "google_product_category": "Móviles y accesorios > Teléfonos móviles"
  },
  {
    "id": "ip15-128-a90",
    "title": "iPhone 15 128GB Usado A+",
    "description": "iPhone 15 128GB · Usado A+ · Batería ≥90%. Garantía QRTech.",
    "availability": "in stock",
    "condition": "used",
    "price": "600.00 USD",
    "color": "",
    "size": "128GB",
    "custom_label_0": "≥90%",
    "item_group_id": "ip15",
    "brand": "Apple",
    "link": "https://qrtech.com.ar/productos?sku=ip15",
    "image_link": "https://qrtech.com.ar/img/productos/15.png",
    "additional_image_link": "",
    "google_product_category": "Móviles y accesorios > Teléfonos móviles"
  },
  {
    "id": "ip15-128-a100",
    "title": "iPhone 15 128GB Usado A+",
    "description": "iPhone 15 128GB · Usado A+ · Batería 100%. Garantía QRTech.",
    "availability": "in stock",
    "condition": "used",
    "price": "630.00 USD",
    "color": "",
    "size": "128GB",
    "custom_label_0": "100%",
    "item_group_id": "ip15",
    "brand": "Apple",
    "link": "https://qrtech.com.ar/productos?sku=ip15",
    "image_link": "https://qrtech.com.ar/img/productos/15.png",
    "additional_image_link": "",
    "google_product_category": "Móviles y accesorios > Teléfonos móviles"
  },
  {
    "id": "ip15p-128-a80",
    "title": "iPhone 15 Pro 128GB Usado A+",
    "description": "iPhone 15 Pro 128GB · Usado A+ · Batería ≥85%. Garantía QRTech.",
    "availability": "in stock",
    "condition": "used",
    "price": "740.00 USD",
    "color": "",
    "size": "128GB",
    "custom_label_0": "≥85%",
    "item_group_id": "ip15p",
    "brand": "Apple",
    "link": "https://qrtech.com.ar/productos?sku=ip15p",
    "image_link": "https://qrtech.com.ar/img/productos/15p.png",
    "additional_image_link": "",
    "google_product_category": "Móviles y accesorios > Teléfonos móviles"
  },
  {
    "id": "ip15p-128-a90",
    "title": "iPhone 15 Pro 128GB Usado A+",
    "description": "iPhone 15 Pro 128GB · Usado A+ · Batería ≥90%. Garantía QRTech.",
    "availability": "in stock",
    "condition": "used",
    "price": "750.00 USD",
    "color": "",
    "size": "128GB",
    "custom_label_0": "≥90%",
    "item_group_id": "ip15p",
    "brand": "Apple",
    "link": "https://qrtech.com.ar/productos?sku=ip15p",
    "image_link": "https://qrtech.com.ar/img/productos/15p.png",
    "additional_image_link": "",
    "google_product_category": "Móviles y accesorios > Teléfonos móviles"
  },
  {
    "id": "ip15p-128-a100",
    "title": "iPhone 15 Pro 128GB Usado A+",
    "description": "iPhone 15 Pro 128GB · Usado A+ · Batería 100%. Garantía QRTech.",
    "availability": "in stock",
    "condition": "used",
    "price": "780.00 USD",
    "color": "",
    "size": "128GB",
    "custom_label_0": "100%",
    "item_group_id": "ip15p",
    "brand": "Apple",
    "link": "https://qrtech.com.ar/productos?sku=ip15p",
    "image_link": "https://qrtech.com.ar/img/productos/15p.png",
    "additional_image_link": "",
    "google_product_category": "Móviles y accesorios > Teléfonos móviles"
  },
  {
    "id": "ip15pm-256-a80",
    "title": "iPhone 15 Pro Max 128GB Usado A+",
    "description": "iPhone 15 Pro Max 128GB · Usado A+ · Batería ≥85%. Garantía QRTech.",
    "availability": "in stock",
    "condition": "used",
    "price": "800.00 USD",
    "color": "",
    "size": "128GB",
    "custom_label_0": "≥85%",
    "item_group_id": "ip15pm",
    "brand": "Apple",
    "link": "https://qrtech.com.ar/productos?sku=ip15pm",
    "image_link": "https://qrtech.com.ar/img/productos/15pm.png",
    "additional_image_link": "",
    "google_product_category": "Móviles y accesorios > Teléfonos móviles"
  },
  {
    "id": "ip15pm-256-a90",
    "title": "iPhone 15 Pro Max 128GB Usado A+",
    "description": "iPhone 15 Pro Max 128GB · Usado A+ · Batería ≥90%. Garantía QRTech.",
    "availability": "in stock",
    "condition": "used",
    "price": "810.00 USD",
    "color": "",
    "size": "128GB",
    "custom_label_0": "≥90%",
    "item_group_id": "ip15pm",
    "brand": "Apple",
    "link": "https://qrtech.com.ar/productos?sku=ip15pm",
    "image_link": "https://qrtech.com.ar/img/productos/15pm.png",
    "additional_image_link": "",
    "google_product_category": "Móviles y accesorios > Teléfonos móviles"
  },
  {
    "id": "ip15pm-256-a100",
    "title": "iPhone 15 Pro Max 128GB Usado A+",
    "description": "iPhone 15 Pro Max 128GB · Usado A+ · Batería 100%. Garantía QRTech.",
    "availability": "in stock",
    "condition": "used",
    "price": "830.00 USD",
    "color": "",
    "size": "128GB",
    "custom_label_0": "100%",
    "item_group_id": "ip15pm",
    "brand": "Apple",
    "link": "https://qrtech.com.ar/productos?sku=ip15pm",
    "image_link": "https://qrtech.com.ar/img/productos/15pm.png",
    "additional_image_link": "",
    "google_product_category": "Móviles y accesorios > Teléfonos móviles"
  },
  {
    "id": "ip16-128-a80",
    "title": "iPhone 16 128GB Usado A+",
    "description": "iPhone 16 128GB · Usado A+ · Batería ≥85%. Garantía QRTech.",
    "availability": "in stock",
    "condition": "used",
    "price": "750.00 USD",
    "color": "",
    "size": "128GB",
    "custom_label_0": "≥85%",
    "item_group_id": "ip16",
    "brand": "Apple",
    "link": "https://qrtech.com.ar/productos?sku=ip16",
    "image_link": "https://qrtech.com.ar/img/productos/16.png",
    "additional_image_link": "",
    "google_product_category": "Móviles y accesorios > Teléfonos móviles"
  },
  {
    "id": "ip16-128-a90",
    "title": "iPhone 16 128GB Usado A+",
    "description": "iPhone 16 128GB · Usado A+ · Batería ≥90%. Garantía QRTech.",
    "availability": "in stock",
    "condition": "used",
    "price": "750.00 USD",
    "color": "",
    "size": "128GB",
    "custom_label_0": "≥90%",
    "item_group_id": "ip16",
    "brand": "Apple",
    "link": "https://qrtech.com.ar/productos?sku=ip16",
    "image_link": "https://qrtech.com.ar/img/productos/16.png",
    "additional_image_link": "",
    "google_product_category": "Móviles y accesorios > Teléfonos móviles"
  },
  {
    "id": "ip16-128-a100",
    "title": "iPhone 16 128GB Usado A+",
    "description": "iPhone 16 128GB · Usado A+ · Batería 100%. Garantía QRTech.",
    "availability": "in stock",
    "condition": "used",
    "price": "750.00 USD",
    "color": "",
    "size": "128GB",
    "custom_label_0": "100%",
    "item_group_id": "ip16",
    "brand": "Apple",
    "link": "https://qrtech.com.ar/productos?sku=ip16",
    "image_link": "https://qrtech.com.ar/img/productos/16.png",
    "additional_image_link": "",
    "google_product_category": "Móviles y accesorios > Teléfonos móviles"
  },
  {
    "id": "ip16e-128-a80",
    "title": "iPhone 16e 128GB Usado A+",
    "description": "iPhone 16e 128GB · Usado A+ · Batería ≥85%. Garantía QRTech.",
    "availability": "in stock",
    "condition": "used",
    "price": "645.00 USD",
    "color": "",
    "size": "128GB",
    "custom_label_0": "≥85%",
    "item_group_id": "ip16e",
    "brand": "Apple",
    "link": "https://qrtech.com.ar/productos?sku=ip16e",
    "image_link": "https://qrtech.com.ar/img/productos/16e.png",
    "additional_image_link": "",
    "google_product_category": "Móviles y accesorios > Teléfonos móviles"
  },
  {
    "id": "ip16e-128-a90",
    "title": "iPhone 16e 128GB Usado A+",
    "description": "iPhone 16e 128GB · Usado A+ · Batería ≥90%. Garantía QRTech.",
    "availability": "in stock",
    "condition": "used",
    "price": "645.00 USD",
    "color": "",
    "size": "128GB",
    "custom_label_0": "≥90%",
    "item_group_id": "ip16e",
    "brand": "Apple",
    "link": "https://qrtech.com.ar/productos?sku=ip16e",
    "image_link": "https://qrtech.com.ar/img/productos/16e.png",
    "additional_image_link": "",
    "google_product_category": "Móviles y accesorios > Teléfonos móviles"
  },
  {
    "id": "ip16e-128-a100",
    "title": "iPhone 16e 128GB Usado A+",
    "description": "iPhone 16e 128GB · Usado A+ · Batería 100%. Garantía QRTech.",
    "availability": "in stock",
    "condition": "used",
    "price": "645.00 USD",
    "color": "",
    "size": "128GB",
    "custom_label_0": "100%",
    "item_group_id": "ip16e",
    "brand": "Apple",
    "link": "https://qrtech.com.ar/productos?sku=ip16e",
    "image_link": "https://qrtech.com.ar/img/productos/16e.png",
    "additional_image_link": "",
    "google_product_category": "Móviles y accesorios > Teléfonos móviles"
  },
  {
    "id": "ip16p-128-a80",
    "title": "iPhone 16 Pro 128GB Usado A+",
    "description": "iPhone 16 Pro 128GB · Usado A+ · Batería ≥85%. Garantía QRTech.",
    "availability": "in stock",
    "condition": "used",
    "price": "920.00 USD",
    "color": "",
    "size": "128GB",
    "custom_label_0": "≥85%",
    "item_group_id": "ip16p",
    "brand": "Apple",
    "link": "https://qrtech.com.ar/productos?sku=ip16p",
    "image_link": "https://qrtech.com.ar/img/productos/16p.png",
    "additional_image_link": "",
    "google_product_category": "Móviles y accesorios > Teléfonos móviles"
  },
  {
    "id": "ip16p-128-a90",
    "title": "iPhone 16 Pro 128GB Usado A+",
    "description": "iPhone 16 Pro 128GB · Usado A+ · Batería ≥90%. Garantía QRTech.",
    "availability": "in stock",
    "condition": "used",
    "price": "920.00 USD",
    "color": "",
    "size": "128GB",
    "custom_label_0": "≥90%",
    "item_group_id": "ip16p",
    "brand": "Apple",
    "link": "https://qrtech.com.ar/productos?sku=ip16p",
    "image_link": "https://qrtech.com.ar/img/productos/16p.png",
    "additional_image_link": "",
    "google_product_category": "Móviles y accesorios > Teléfonos móviles"
  },
  {
    "id": "ip16p-128-a100",
    "title": "iPhone 16 Pro 128GB Usado A+",
    "description": "iPhone 16 Pro 128GB · Usado A+ · Batería 100%. Garantía QRTech.",
    "availability": "in stock",
    "condition": "used",
    "price": "920.00 USD",
    "color": "",
    "size": "128GB",
    "custom_label_0": "100%",
    "item_group_id": "ip16p",
    "brand": "Apple",
    "link": "https://qrtech.com.ar/productos?sku=ip16p",
    "image_link": "https://qrtech.com.ar/img/productos/16p.png",
    "additional_image_link": "",
    "google_product_category": "Móviles y accesorios > Teléfonos móviles"
  },
  {
    "id": "ip16pm-256-a80",
    "title": "iPhone 16 Pro Max 128GB Usado A+",
    "description": "iPhone 16 Pro Max 128GB · Usado A+ · Batería ≥85%. Garantía QRTech.",
    "availability": "in stock",
    "condition": "used",
    "price": "1110.00 USD",
    "color": "",
    "size": "128GB",
    "custom_label_0": "≥85%",
    "item_group_id": "ip16pm",
    "brand": "Apple",
    "link": "https://qrtech.com.ar/productos?sku=ip16pm",
    "image_link": "https://qrtech.com.ar/img/productos/16pm.png",
    "additional_image_link": "",
    "google_product_category": "Móviles y accesorios > Teléfonos móviles"
  },
  {
    "id": "ip16pm-256-a90",
    "title": "iPhone 16 Pro Max 128GB Usado A+",
    "description": "iPhone 16 Pro Max 128GB · Usado A+ · Batería ≥90%. Garantía QRTech.",
    "availability": "in stock",
    "condition": "used",
    "price": "1110.00 USD",
    "color": "",
    "size": "128GB",
    "custom_label_0": "≥90%",
    "item_group_id": "ip16pm",
    "brand": "Apple",
    "link": "https://qrtech.com.ar/productos?sku=ip16pm",
    "image_link": "https://qrtech.com.ar/img/productos/16pm.png",
    "additional_image_link": "",
    "google_product_category": "Móviles y accesorios > Teléfonos móviles"
  },
  {
    "id": "ip16pm-256-a100",
    "title": "iPhone 16 Pro Max 128GB Usado A+",
    "description": "iPhone 16 Pro Max 128GB · Usado A+ · Batería 100%. Garantía QRTech.",
    "availability": "in stock",
    "condition": "used",
    "price": "1110.00 USD",
    "color": "",
    "size": "128GB",
    "custom_label_0": "100%",
    "item_group_id": "ip16pm",
    "brand": "Apple",
    "link": "https://qrtech.com.ar/productos?sku=ip16pm",
    "image_link": "https://qrtech.com.ar/img/productos/16pm.png",
    "additional_image_link": "",
    "google_product_category": "Móviles y accesorios > Teléfonos móviles"
  },
  {
    "id": "redmi-14c-128-nuevo",
    "title": "Redmi 14C 4GB / 128GB 128GB Nuevo",
    "description": "Redmi 14C 4GB / 128GB 128GB · Nuevo · Batería —. Garantía QRTech.",
    "availability": "in stock",
    "condition": "used",
    "price": "175.00 USD",
    "color": "",
    "size": "128GB",
    "custom_label_0": "—",
    "item_group_id": "redmi-14c-4-128",
    "brand": "Xiaomi",
    "link": "https://qrtech.com.ar/productos?sku=redmi-14c-4-128",
    "image_link": "https://qrtech.com.ar/img/productos/redmi-14c.png",
    "additional_image_link": "",
    "google_product_category": "Móviles y accesorios > Teléfonos móviles"
  },
  {
    "id": "redmi-14c-256-nuevo",
    "title": "Redmi 14C 8GB / 256GB 256GB Nuevo",
    "description": "Redmi 14C 8GB / 256GB 256GB · Nuevo · Batería —. Garantía QRTech.",
    "availability": "in stock",
    "condition": "used",
    "price": "198.00 USD",
    "color": "",
    "size": "256GB",
    "custom_label_0": "—",
    "item_group_id": "redmi-14c-8-256",
    "brand": "Xiaomi",
    "link": "https://qrtech.com.ar/productos?sku=redmi-14c-8-256",
    "image_link": "https://qrtech.com.ar/img/productos/redmi-14c2.png",
    "additional_image_link": "",
    "google_product_category": "Móviles y accesorios > Teléfonos móviles"
  },
  {
    "id": "redmi-note-14-256-nuevo",
    "title": "Redmi Note 14 8GB / 256GB 256GB Nuevo",
    "description": "Redmi Note 14 8GB / 256GB 256GB · Nuevo · Batería —. Garantía QRTech.",
    "availability": "in stock",
    "condition": "used",
    "price": "240.00 USD",
    "color": "",
    "size": "256GB",
    "custom_label_0": "—",
    "item_group_id": "redmi-note-14-8-256",
    "brand": "Xiaomi",
    "link": "https://qrtech.com.ar/productos?sku=redmi-note-14-8-256",
    "image_link": "https://qrtech.com.ar/img/productos/redmi-note-14.png",
    "additional_image_link": "",
    "google_product_category": "Móviles y accesorios > Teléfonos móviles"
  },
  {
    "id": "redmi-note-14-pro-256-nuevo",
    "title": "Redmi Note 14 Pro 8GB / 256GB 256GB Nuevo",
    "description": "Redmi Note 14 Pro 8GB / 256GB 256GB · Nuevo · Batería —. Garantía QRTech.",
    "availability": "in stock",
    "condition": "used",
    "price": "283.00 USD",
    "color": "",
    "size": "256GB",
    "custom_label_0": "—",
    "item_group_id": "redmi-note-14-pro-8-256",
    "brand": "Xiaomi",
    "link": "https://qrtech.com.ar/productos?sku=redmi-note-14-pro-8-256",
    "image_link": "https://qrtech.com.ar/img/productos/redmi-note-14p.png",
    "additional_image_link": "",
    "google_product_category": "Móviles y accesorios > Teléfonos móviles"
  },
  {
    "id": "sm-a06-64-nuevo",
    "title": "Samsung Galaxy A06 4GB / 64GB 64GB Nuevo",
    "description": "Samsung Galaxy A06 4GB / 64GB 64GB · Nuevo · Batería —. Garantía QRTech.",
    "availability": "in stock",
    "condition": "used",
    "price": "167.00 USD",
    "color": "",
    "size": "64GB",
    "custom_label_0": "—",
    "item_group_id": "sm-a06-4-64",
    "brand": "Samsung",
    "link": "https://qrtech.com.ar/productos?sku=sm-a06-4-64",
    "image_link": "https://qrtech.com.ar/img/productos/smg-a06.png",
    "additional_image_link": "",
    "google_product_category": "Móviles y accesorios > Teléfonos móviles"
  },
  {
    "id": "sm-a16-6-256",
    "title": "Samsung Galaxy A16 6GB / 256GB",
    "description": "Samsung Galaxy A16 6GB / 256GB · Garantía QRTech.",
    "availability": "in stock",
    "condition": "used",
    "price": "270.00 USD",
    "color": "",
    "size": "",
    "custom_label_0": "",
    "item_group_id": "sm-a16-6-256",
    "brand": "Samsung",
    "link": "https://qrtech.com.ar/productos?sku=sm-a16-6-256",
    "image_link": "https://qrtech.com.ar/img/productos/smg-a16.png",
    "additional_image_link": "",
    "google_product_category": "Móviles y accesorios > Teléfonos móviles"
  },
  {
    "id": "sm-a36-256-nuevo",
    "title": "Samsung Galaxy A36 8GB / 256GB 256GB Nuevo",
    "description": "Samsung Galaxy A36 8GB / 256GB 256GB · Nuevo · Batería —. Garantía QRTech.",
    "availability": "in stock",
    "condition": "used",
    "price": "365.00 USD",
    "color": "",
    "size": "256GB",
    "custom_label_0": "—",
    "item_group_id": "sm-a36-8-256",
    "brand": "Samsung",
    "link": "https://qrtech.com.ar/productos?sku=sm-a36-8-256",
    "image_link": "https://qrtech.com.ar/img/productos/smg-a36.png",
    "additional_image_link": "",
    "google_product_category": "Móviles y accesorios > Teléfonos móviles"
  },
  {
    "id": "sm-a56-256-nuevo",
    "title": "Samsung Galaxy A56 8GB / 256GB 256GB Nuevo",
    "description": "Samsung Galaxy A56 8GB / 256GB 256GB · Nuevo · Batería —. Garantía QRTech.",
    "availability": "in stock",
    "condition": "used",
    "price": "455.00 USD",
    "color": "",
    "size": "256GB",
    "custom_label_0": "—",
    "item_group_id": "sm-a56-8-256",
    "brand": "Samsung",
    "link": "https://qrtech.com.ar/productos?sku=sm-a56-8-256",
    "image_link": "https://qrtech.com.ar/img/productos/smg-a56.png",
    "additional_image_link": "",
    "google_product_category": "Móviles y accesorios > Teléfonos móviles"
  },
  {
    "id": "cbl-usbc-lightning",
    "title": "Cable USB-C a Lightning 1m (Alta calidad)",
    "description": "Cable USB-C a Lightning 1m (Alta calidad) · Garantía QRTech.",
    "availability": "in stock",
    "condition": "used",
    "price": "5.00 USD",
    "color": "",
    "size": "",
    "custom_label_0": "",
    "item_group_id": "cbl-usbc-lightning-1m",
    "brand": "Genérica",
    "link": "https://qrtech.com.ar/productos?sku=cbl-usbc-lightning-1m",
    "image_link": "https://qrtech.com.ar/img/productos/cbl-usbc-lightning.png",
    "additional_image_link": "",
    "google_product_category": "Móviles y accesorios > Teléfonos móviles"
  },
  {
    "id": "cbl-usbc-usbc",
    "title": "Cable USB-C a USB-C 1m (Carga rápida)",
    "description": "Cable USB-C a USB-C 1m (Carga rápida) · Garantía QRTech.",
    "availability": "in stock",
    "condition": "used",
    "price": "5.00 USD",
    "color": "",
    "size": "",
    "custom_label_0": "",
    "item_group_id": "cbl-usbc-usbc-1m",
    "brand": "Genérica",
    "link": "https://qrtech.com.ar/productos?sku=cbl-usbc-usbc-1m",
    "image_link": "https://qrtech.com.ar/img/productos/cbl-usbc-usbc.png",
    "additional_image_link": "",
    "google_product_category": "Móviles y accesorios > Teléfonos móviles"
  },
  {
    "id": "cbl-usba-lightning",
    "title": "Cable USB-A a Lightning 1m",
    "description": "Cable USB-A a Lightning 1m · Garantía QRTech.",
    "availability": "in stock",
    "condition": "used",
    "price": "5.00 USD",
    "color": "",
    "size": "",
    "custom_label_0": "",
    "item_group_id": "cbl-usba-lightning-1m",
    "brand": "Genérica",
    "link": "https://qrtech.com.ar/productos?sku=cbl-usba-lightning-1m",
    "image_link": "https://qrtech.com.ar/img/productos/cbl-usba-lightning.png",
    "additional_image_link": "",
    "google_product_category": "Móviles y accesorios > Teléfonos móviles"
  },
  {
    "id": "chg-iphone-20w",
    "title": "Cargador iPhone 20W USB-C (fuente)",
    "description": "Cargador iPhone 20W USB-C (fuente) · Garantía QRTech.",
    "availability": "in stock",
    "condition": "used",
    "price": "12.00 USD",
    "color": "",
    "size": "",
    "custom_label_0": "",
    "item_group_id": "chg-iphone-20w-usbc",
    "brand": "Genérica",
    "link": "https://qrtech.com.ar/productos?sku=chg-iphone-20w-usbc",
    "image_link": "https://qrtech.com.ar/img/productos/chg-iphone-20w.png",
    "additional_image_link": "",
    "google_product_category": "Móviles y accesorios > Teléfonos móviles"
  },
  {
    "id": "pbank-magsafe",
    "title": "Power Bank MagSafe 10000 mAh",
    "description": "Power Bank MagSafe 10000 mAh · Garantía QRTech.",
    "availability": "in stock",
    "condition": "used",
    "price": "25.00 USD",
    "color": "",
    "size": "",
    "custom_label_0": "",
    "item_group_id": "pbank-magsafe-10000",
    "brand": "Genérica",
    "link": "https://qrtech.com.ar/productos?sku=pbank-magsafe-10000",
    "image_link": "https://qrtech.com.ar/img/productos/pbank-magsafe.png",
    "additional_image_link": "",
    "google_product_category": "Móviles y accesorios > Teléfonos móviles"
  },
  {
    "id": "m90pro",
    "title": "Auriculares M90 Pro Bluetooth",
    "description": "Auriculares M90 Pro Bluetooth · Garantía QRTech.",
    "availability": "in stock",
    "condition": "used",
    "price": "10.00 USD",
    "color": "",
    "size": "",
    "custom_label_0": "",
    "item_group_id": "m90pro-bluetooth",
    "brand": "M90",
    "link": "https://qrtech.com.ar/productos?sku=m90pro-bluetooth",
    "image_link": "https://qrtech.com.ar/img/productos/m90pro.png",
    "additional_image_link": "",
    "google_product_category": "Móviles y accesorios > Teléfonos móviles"
  }
]